[
    {
        "name":  "4TV News (576p)",
        "tvgId":  "4TVNews.in@SD",
        "tvgName":  "4TV News (576p)",
        "logo":  "https://i.imgur.com/DSAaC2b.png",
        "category":  "News",
        "url":  "https://cdn-4.pishow.tv/live/1007/master.m3u8"
    },
    {
        "name":  "9X Jalwa (1080p)",
        "tvgId":  "9XJalwa.in@SD",
        "tvgName":  "9X Jalwa (1080p)",
        "logo":  "https://i.imgur.com/qubgOi5.png",
        "category":  "Music",
        "url":  "https://d35j504z0x2vu2.cloudfront.net/v1/master/0bc8e8376bd8417a1b6761138aa41c26c7309312/9x-jalwa/master.m3u8"
    },
    {
        "name":  "9x Jhakaas",
        "tvgId":  "9XJhakaas.in@SD",
        "tvgName":  "9x Jhakaas",
        "logo":  "https://i.imgur.com/aZ0f85I.png",
        "category":  "Music",
        "url":  "https://amg01281-9xmediapvtltd-9xjhakaas-samsungin-ci2cs.amagi.tv/playlist/amg01281-9xmediapvtltd-9xjhakaas-samsungin/playlist.m3u8"
    },
    {
        "name":  "9X Tashan",
        "tvgId":  "9XTashan.in@SD",
        "tvgName":  "9X Tashan",
        "logo":  "https://i.imgur.com/MMR1RMF.png",
        "category":  "Music",
        "url":  "https://amg01281-9xmediapvtltd-9xtashan-samsungin-xz1sd.amagi.tv/playlist/amg01281-9xmediapvtltd-9xtashan-samsungin/playlist.m3u8"
    },
    {
        "name":  "9XM (576p)",
        "tvgId":  "9XM.in@SD",
        "tvgName":  "9XM (576p)",
        "logo":  "https://i.imgur.com/F17QtN2.png",
        "category":  "Music",
        "url":  "https://d35j504z0x2vu2.cloudfront.net/v1/manifest/0bc8e8376bd8417a1b6761138aa41c26c7309312/9xm/23886666-8fc5-470f-aab1-bd637ed607b1/3.m3u8"
    },
    {
        "name":  "10 TV (720p)",
        "tvgId":  "10TV.in@SD",
        "tvgName":  "10 TV (720p)",
        "logo":  "https://i.imgur.com/TauWtuJ.png",
        "category":  "News",
        "url":  "https://cdn-1.pishow.tv/live/391/master.m3u8"
    },
    {
        "name":  "99TV (720p)",
        "tvgId":  "99TV.in@SD",
        "tvgName":  "99TV (720p)",
        "logo":  "https://i.imgur.com/dZA4gel.png",
        "category":  "News",
        "url":  "https://cdn-1.pishow.tv/live/1211/master.m3u8"
    },
    {
        "name":  "\u0026flix (480p)",
        "tvgId":  "Andflix.in@SD",
        "tvgName":  "\u0026flix (480p)",
        "logo":  "https://upload.wikimedia.org/wikipedia/commons/thumb/e/ec/%26flix_2025.svg/512px-%26flix_2025.svg.png",
        "category":  "Movies",
        "url":  "https://edge3-moblive.yuppcdn.net/drm/smil:nflixdrm.smil/index.m3u8"
    },
    {
        "name":  "\u0026TV (1080p)",
        "tvgId":  "AndTV.in@SD",
        "tvgName":  "\u0026TV (1080p)",
        "logo":  "https://i.imgur.com/32W50Y6.png",
        "category":  "Movies",
        "url":  "https://amg01117-amg01117c1-amgplt0165.playout.now3.amagi.tv/playlist.m3u8"
    },
    {
        "name":  "Aaj Tak (1080p)",
        "tvgId":  "AajTak.in@SD",
        "tvgName":  "Aaj Tak (1080p)",
        "logo":  "https://i.imgur.com/RpIdCB3.png",
        "category":  "News",
        "url":  "https://livehub-voidnet.onrender.com/cluster/streamcore/in/AAJTAK_REDIS.m3u8"
    },
    {
        "name":  "Aakaash Aath (720p)",
        "tvgId":  "AakaashAath.in@SD",
        "tvgName":  "Aakaash Aath (720p)",
        "logo":  "https://i.imgur.com/rAAgfJ4.png",
        "category":  "Entertainment",
        "url":  "https://cdn-4.pishow.tv/live/969/master.m3u8"
    },
    {
        "name":  "Aamar Bangla (720p)",
        "tvgId":  "AamarBangla.in@SD",
        "tvgName":  "Aamar Bangla (720p)",
        "logo":  "https://www.jagobd.com/wp-content/uploads/2022/07/Aamar-Bangla.jpg",
        "category":  "Entertainment",
        "url":  "https://live-stream.utkalbongo.com/utkalbongo/stream10/hls/amarbangla.m3u8"
    },
    {
        "name":  "Aastha (480p)",
        "tvgId":  "Aastha.in@SD",
        "tvgName":  "Aastha (480p)",
        "logo":  "https://i.imgur.com/IqgrV92.png",
        "category":  "Religious",
        "url":  "https://aasthaott.akamaized.net/110923/smil:aasthatv.smil/chunklist_b1328000.m3u8"
    },
    {
        "name":  "Aastha Bhajan (480p)",
        "tvgId":  "AasthaBhajan.in@SD",
        "tvgName":  "Aastha Bhajan (480p)",
        "logo":  "https://i.imgur.com/LyDxqnF.png",
        "category":  "Religious",
        "url":  "https://aasthaott.akamaized.net/110923/smil:bhajan.smil/playlist.m3u8"
    },
    {
        "name":  "ABN Andhra Jyoti (720p)",
        "tvgId":  "ABNAndhraJyoti.in@SD",
        "tvgName":  "ABN Andhra Jyoti (720p)",
        "logo":  "https://i.imgur.com/gcoiZJ3.png",
        "category":  "News",
        "url":  "https://cdn-1.pishow.tv/live/407/master.m3u8"
    },
    {
        "name":  "ABN TV India (540p)",
        "tvgId":  "ABNTVIndia.us@SD",
        "tvgName":  "ABN TV India (540p)",
        "logo":  "https://i.imgur.com/VcZn60X.png",
        "category":  "Religious",
        "url":  "https://mediaserver.abnvideos.com/streams/abntvindia.m3u8"
    },
    {
        "name":  "ABP Ananda (1080p)",
        "tvgId":  "ABPAnanda.in@SD",
        "tvgName":  "ABP Ananda (1080p)",
        "logo":  "https://upload.wikimedia.org/wikipedia/commons/thumb/c/cd/ABP_Ananda_logo.svg/512px-ABP_Ananda_logo.svg.png",
        "category":  "News",
        "url":  "https://d35j504z0x2vu2.cloudfront.net/v1/master/0bc8e8376bd8417a1b6761138aa41c26c7309312/abp-ananda/master.m3u8"
    },
    {
        "name":  "ABP Asmita (1080p)",
        "tvgId":  "ABPAsmita.in@SD",
        "tvgName":  "ABP Asmita (1080p)",
        "logo":  "https://upload.wikimedia.org/wikipedia/commons/thumb/2/20/ABP_Asmita_logo.svg/512px-ABP_Asmita_logo.svg.png",
        "category":  "News",
        "url":  "https://d35j504z0x2vu2.cloudfront.net/v1/master/0bc8e8376bd8417a1b6761138aa41c26c7309312/abp-asmita/master.m3u8"
    },
    {
        "name":  "ABP Ganga (1080p)",
        "tvgId":  "ABPGanga.in@SD",
        "tvgName":  "ABP Ganga (1080p)",
        "logo":  "https://upload.wikimedia.org/wikipedia/commons/thumb/c/cf/ABP_Ganga.svg/512px-ABP_Ganga.svg.png",
        "category":  "News",
        "url":  "https://abplivetv.akamaized.net/hls/live/2043013/ganga/master.m3u8"
    },
    {
        "name":  "ABP Majha (360p)",
        "tvgId":  "ABPMajha.in@SD",
        "tvgName":  "ABP Majha (360p)",
        "logo":  "https://upload.wikimedia.org/wikipedia/commons/thumb/5/55/ABP_Majha_logo.svg/512px-ABP_Majha_logo.svg.png",
        "category":  "News",
        "url":  "https://in1.sunilprasad.com.np/yuppLive/abp-majha/master.m3u8"
    },
    {
        "name":  "ABP Sanjha (720p)",
        "tvgId":  "ABPSanjha.in@SD",
        "tvgName":  "ABP Sanjha (720p)",
        "logo":  "https://upload.wikimedia.org/wikipedia/commons/thumb/8/80/ABP_Sanjha_logo.svg/512px-ABP_Sanjha_logo.svg.png",
        "category":  "News",
        "url":  "https://d35j504z0x2vu2.cloudfront.net/v1/master/0bc8e8376bd8417a1b6761138aa41c26c7309312/abp-sanjha/master.m3u8"
    },
    {
        "name":  "Abzy Dhakad (480p)",
        "tvgId":  "AbzyDhakad.in@SD",
        "tvgName":  "Abzy Dhakad (480p)",
        "logo":  "https://i.imgur.com/5ORC4tn.png",
        "category":  "Movies",
        "url":  "https://d2lk5u59tns74c.cloudfront.net/out/v1/4fe6ab07a13543d6bdb2ec63b3e2df44/index.m3u8"
    },
    {
        "name":  "Abzy Movies (480p)",
        "tvgId":  "AbzyMovies.in@SD",
        "tvgName":  "Abzy Movies (480p)",
        "logo":  "https://i.imgur.com/LnVgKVF.png",
        "category":  "Movies",
        "url":  "https://d3qs3d2rkhfqrt.cloudfront.net/out/v1/db8d4eca72d64748a00d0631debf542d/index.m3u8"
    },
    {
        "name":  "AKD Calcutta News (576p)",
        "tvgId":  "AKDCalcuttaNews.in@SD",
        "tvgName":  "AKD Calcutta News (576p)",
        "logo":  "https://i.imgur.com/7Kl95WA.png",
        "category":  "News",
        "url":  "https://cdn-2.pishow.tv/live/237/master.m3u8"
    },
    {
        "name":  "Alankar TV (720p)",
        "tvgId":  "AlankarTV.in@SD",
        "tvgName":  "Alankar TV (720p)",
        "logo":  "https://i.imgur.com/fY3ApRs.png",
        "category":  "Entertainment",
        "url":  "https://livetv.tarangplus.in/alankar-origin/live/playlist.m3u8"
    },
    {
        "name":  "Amrita TV (720p)",
        "tvgId":  "AmritaTV.in@SD",
        "tvgName":  "Amrita TV (720p)",
        "logo":  "https://i.imgur.com/WdSjlPl.png",
        "category":  "Entertainment",
        "url":  "https://ddash74r36xqp.cloudfront.net/master.m3u8"
    },
    {
        "name":  "Anandham TV (1080p)",
        "tvgId":  "AnandhamTV.in@SD",
        "tvgName":  "Anandham TV (1080p)",
        "logo":  "https://jiotvimages.cdn.jio.com/dare_images/shows/2025-11-25/2511253358000.jpg",
        "category":  "Movies",
        "url":  "https://stream.galaxyott.live/live/anandhamtv/index.m3u8"
    },
    {
        "name":  "Angel TV (720p)",
        "tvgId":  "AngelTV.in@India",
        "tvgName":  "Angel TV (720p)",
        "logo":  "https://i.imgur.com/qKLEGU7.png",
        "category":  "Religious",
        "url":  "https://janya-digimix.akamaized.net/vglive-sk-394914/india/ngrp:angelindia_all/playlist.m3u8"
    },
    {
        "name":  "Animax [Geo-blocked]",
        "tvgId":  "Animax.in@SD",
        "tvgName":  "Animax [Geo-blocked]",
        "logo":  "https://upload.wikimedia.org/wikipedia/commons/thumb/6/6f/Animax.png/512px-Animax.png",
        "category":  "Animation",
        "url":  "https://amg02159-kcglobal-amg02159c1-samsung-in-521.playouts.now.amagi.tv/playlist/amg02159-kcglobal-animax-samsungin/playlist.m3u8"
    },
    {
        "name":  "Anjan (1080p) [Not 24/7]",
        "tvgId":  "AnjanTV.in@SD",
        "tvgName":  "Anjan (1080p) [Not 24/7]",
        "logo":  "https://i.imgur.com/sh0yFSf.png",
        "category":  "Entertainment",
        "url":  "https://anjantvevent.pc.cdn.bitgravity.com/anjantv/live/amlst:event_anjan_,b400,b800,b1024,b1200,b1500,b4000,.smil/playlist.m3u8"
    },
    {
        "name":  "ANN News (720p)",
        "tvgId":  "ANNNews.in@HD",
        "tvgName":  "ANN News (720p)",
        "logo":  "https://asianewsnetwork.net/wp-content/uploads/2020/03/cropped-LOGO-NEW.png",
        "category":  "News",
        "url":  "https://cdn.ottlive.co.in/annnews/index.m3u8"
    },
    {
        "name":  "Apna Punjab TV (720p)",
        "tvgId":  "ApnaPunjabTV.ca@SD",
        "tvgName":  "Apna Punjab TV (720p)",
        "logo":  "https://i.imgur.com/IM4D8Wz.png",
        "category":  "Entertainment",
        "url":  "https://plus.gigabitcdn.net/live-stream/apna-punjab-H3sE/playlist.m3u8"
    },
    {
        "name":  "Aradana TV (576p)",
        "tvgId":  "AradanaTV.in@SD",
        "tvgName":  "Aradana TV (576p)",
        "logo":  "https://i.imgur.com/w48yzLu.png",
        "category":  "Religious",
        "url":  "https://cdn-1.pishow.tv/live/961/master.m3u8"
    },
    {
        "name":  "Ashrafi Channel (484p) [Not 24/7]",
        "tvgId":  "AshrafiChannel.in@SD",
        "tvgName":  "Ashrafi Channel (484p) [Not 24/7]",
        "logo":  "https://i.imgur.com/IXpFcJA.png",
        "category":  "Religious",
        "url":  "https://ashrafichannel.livebox.co.in/ashrafivhannelhls/live.m3u8"
    },
    {
        "name":  "Asianet News (360p)",
        "tvgId":  "AsianetNews.in@SD",
        "tvgName":  "Asianet News (360p)",
        "logo":  "https://i.imgur.com/LrHGfdC.png",
        "category":  "News",
        "url":  "https://asianetnews.vgcdn.net/ptnr-Embed/v1/manifest/611d79b11b77e2f571934fd80ca1413453772ac7/1c19363c-e4a0-4e4d-ba28-771d5615b88e/9bd4a057-456d-43de-b887-7b87b021f1cc/3.m3u8"
    },
    {
        "name":  "Ayush TV (360p) [Not 24/7]",
        "tvgId":  "AyushTV.in@SD",
        "tvgName":  "Ayush TV (360p) [Not 24/7]",
        "logo":  "https://i.imgur.com/PWzvp0B.png",
        "category":  "Lifestyle",
        "url":  "https://95eryw39dwn4-hls-live.wmncdn.net/Ayushu/271ddf829afeece44d8732757fba1a66.sdp/index.m3u8"
    },
    {
        "name":  "B4U Bhojpuri (1080p)",
        "tvgId":  "B4UBhojpuri.in@SD",
        "tvgName":  "B4U Bhojpuri (1080p)",
        "logo":  "https://i.imgur.com/NwOQUDp.png",
        "category":  "Movies",
        "url":  "https://cdnb4u.wiseplayout.com/B4U_Bhojpuri/master.m3u8"
    },
    {
        "name":  "B4U Kadak (1080p) [Not 24/7]",
        "tvgId":  "B4UKadak.in@SD",
        "tvgName":  "B4U Kadak (1080p) [Not 24/7]",
        "logo":  "https://i.imgur.com/CKLn0ft.png",
        "category":  "Movies",
        "url":  "https://cdnb4u.wiseplayout.com/B4U_Kadak/master.m3u8"
    },
    {
        "name":  "B4U Movies India (1080p)",
        "tvgId":  "B4UMovies.in@India",
        "tvgName":  "B4U Movies India (1080p)",
        "logo":  "https://i.imgur.com/M9kMFJl.png",
        "category":  "Movies",
        "url":  "https://cdnb4u.wiseplayout.com/B4U_Movies/master.m3u8"
    },
    {
        "name":  "B4U Music (1080p)",
        "tvgId":  "B4UMusic.in@India",
        "tvgName":  "B4U Music (1080p)",
        "logo":  "https://i.imgur.com/KSxPLJA.png",
        "category":  "Music",
        "url":  "https://cdnb4u.wiseplayout.com/B4U_Music/master.m3u8"
    },
    {
        "name":  "Bada Khabar (432p)",
        "tvgId":  "BadaKhabar.in@SD",
        "tvgName":  "Bada Khabar (432p)",
        "logo":  "https://i.imgur.com/XiwygDJ.png",
        "category":  "News",
        "url":  "https://app.ashokadigital.net/badakhabar/badakhabar/index.m3u8"
    },
    {
        "name":  "Balle Balle (720p)",
        "tvgId":  "BalleBalle.in@SD",
        "tvgName":  "Balle Balle (720p)",
        "logo":  "https://i.imgur.com/oxkkWH5.png",
        "category":  "Music",
        "url":  "https://mcncdndigital.com/balleballetv/index.m3u8"
    },
    {
        "name":  "Bansal News (576p)",
        "tvgId":  "BansalNews.in@SD",
        "tvgName":  "Bansal News (576p)",
        "logo":  "https://i.imgur.com/8QL8SiB.png",
        "category":  "News",
        "url":  "https://yuppftalive.akamaized.net/080823/bansalnews/playlist.m3u8"
    },
    {
        "name":  "Bhakthi TV (720p)",
        "tvgId":  "BhakthiTV.in@SD",
        "tvgName":  "Bhakthi TV (720p)",
        "logo":  "https://upload.wikimedia.org/wikipedia/en/6/61/Bhakthi_TV_logo.jpg",
        "category":  "Undefined",
        "url":  "https://cdn-1.pishow.tv/live/397/master.m3u8"
    },
    {
        "name":  "Bharat Express (480p)",
        "tvgId":  "BharatExpress.in@SD",
        "tvgName":  "Bharat Express (480p)",
        "logo":  "https://bharatexpress.com/wp-content/themes/newstrackcms/images/bharat-express-new-logo.png",
        "category":  "News",
        "url":  "https://stream1.livebox.co.in/VCAREhls/live.m3u8"
    },
    {
        "name":  "Bhojpuri Cinema (720p)",
        "tvgId":  "BhojpuriCinema.in@SD",
        "tvgName":  "Bhojpuri Cinema (720p)",
        "logo":  "https://i.imgur.com/ABxIO7r.jpg",
        "category":  "Movies",
        "url":  "https://live-bhojpuri.akamaized.net/liveabr/playlist.m3u8"
    },
    {
        "name":  "BIG TV (720p)",
        "tvgId":  "BIGTV.in@SD",
        "tvgName":  "BIG TV (720p)",
        "logo":  "https://static.wikia.nocookie.net/logopedia/images/4/4f/BiG_TV_%28Stacked%29.svg/revision/latest/scale-to-width-down/250?cb=20180316124023",
        "category":  "News",
        "url":  "https://cdn-1.pishow.tv/live/1059/master.m3u8"
    },
    {
        "name":  "BTV News (720p) [Not 24/7]",
        "tvgId":  "BtvNews.in@SD",
        "tvgName":  "BTV News (720p) [Not 24/7]",
        "logo":  "https://i.imgur.com/0BEPrNQ.png",
        "category":  "News",
        "url":  "https://vidcdn.vidgyor.com/btv-origin/liveabr/playlist.m3u8"
    },
    {
        "name":  "Calvary TV (720p)",
        "tvgId":  "CalvaryTV.in@SD",
        "tvgName":  "Calvary TV (720p)",
        "logo":  "https://i.imgur.com/BvQzwSp.png",
        "category":  "Undefined",
        "url":  "https://player.mslivestream.net/mslive/71e7f7cc7dc7c51206b7b3bbb51e3052.sdp/playlist.m3u8"
    },
    {
        "name":  "CCV (480p)",
        "tvgId":  "CCV.in@SD",
        "tvgName":  "CCV (480p)",
        "logo":  "https://i.imgur.com/4ss0KfA.png",
        "category":  "General",
        "url":  "https://5a1178b42cc03.streamlock.net/8212/8212/playlist.m3u8"
    }
]
